seo/__init__.py
seo/admin.py
seo/forms.py
seo/importpath.py
seo/managers.py
seo/models.py
seo/locale/ru/LC_MESSAGES/django.mo
seo/locale/ru/LC_MESSAGES/django.po
seo/migrations/0001_initial.py
seo/migrations/__init__.py
seo/south_migrations/0001_initial.py
seo/south_migrations/0002_auto__add_unique_seo_object_id_content_type.py
seo/south_migrations/0003_auto__add_field_seo_site__add_field_url_site__del_unique_url_url__add_.py
seo/south_migrations/0004_auto__del_url__del_unique_url_url_site.py
seo/south_migrations/0005_auto__del_field_seo_site.py
seo/south_migrations/0006_auto__add_url__add_unique_url_site_url.py
seo/south_migrations/0007_auto__del_unique_url_url.py
seo/south_migrations/__init__.py
seo/templatetags/__init__.py
seo/templatetags/seo_tags.py
django_easy_seo-0.4.8.dist-info/AUTHORS.rst
django_easy_seo-0.4.8.dist-info/LICENSE
django_easy_seo-0.4.8.dist-info/METADATA
django_easy_seo-0.4.8.dist-info/WHEEL
django_easy_seo-0.4.8.dist-info/top_level.txt
django_easy_seo-0.4.8.dist-info/RECORD
