Metadata-Version: 2.1
Name: django-easy-seo
Version: 0.4.8
Summary: Adds generic SEO fields for objects in your site
Home-page: https://github.com/bashu/django-easy-seo
Author: Alexander Ivanov
Author-email: alexander.ivanov@redsolution.ru
Maintainer: Basil Shubin
Maintainer-email: basil.shubin@gmail.com
License: GPLv3 License
Download-URL: https://github.com/bashu/django-easy-seo/zipball/master
Platform: UNKNOWN
Classifier: Development Status :: 4 - Beta
Classifier: Environment :: Web Environment
Classifier: Framework :: Django
Classifier: Intended Audience :: Developers
Classifier: License :: OSI Approved :: GNU General Public License (GPL)
Classifier: Operating System :: OS Independent
Classifier: Programming Language :: Python
Classifier: Programming Language :: Python :: 2.6
Classifier: Programming Language :: Python :: 2.7
Classifier: Programming Language :: Python :: 3
Classifier: Programming Language :: Python :: 3.3
Classifier: Topic :: Internet :: WWW/HTTP
Classifier: Topic :: Internet :: WWW/HTTP :: Dynamic Content
Classifier: Topic :: Internet :: WWW/HTTP :: Indexing/Search
Classifier: Topic :: Software Development :: Libraries :: Python Modules
Requires: Django (>=1.4)
Requires-Dist: django-classy-tags
